langchain_stackspot_ai/__init__.py
langchain_stackspot_ai/adapters/__init__.py
langchain_stackspot_ai/adapters/function_adapter.py
langchain_stackspot_ai/adapters/output_parser.py
langchain_stackspot_ai/agents/__init__.py
langchain_stackspot_ai/agents/agent_executor.py
langchain_stackspot_ai/models/__init__.py
langchain_stackspot_ai/models/chat_stackspot_ai.py
langchain_stackspot_ai/utils/__init__.py
langchain_stackspot_ai/utils/logger.py
langchain_stackspot_ai/utils/logging_config.py
langchain_stackspot_ai-0.0.1.dist-info/LICENSE
langchain_stackspot_ai-0.0.1.dist-info/WHEEL
langchain_stackspot_ai-0.0.1.dist-info/METADATA
langchain_stackspot_ai-0.0.1.dist-info/RECORD
