Metadata-Version: 2.1
Name: langchain-stackspot-ai
Version: 0.0.1
Summary: A library for integrating StackSpot AI with LangChain
Home-page: https://github.com/stackspot/langchain-stackspot-ai
License: MIT
Author: Guilherme Chafy
Author-email: guichafy@gmail.com
Requires-Python: >=3.11,<4.0
Classifier: Development Status :: 3 - Alpha
Classifier: Intended Audience :: Developers
Classifier: License :: OSI Approved :: MIT License
Classifier: Programming Language :: Python :: 3
Classifier: Programming Language :: Python :: 3.11
Classifier: Programming Language :: Python :: 3
Classifier: Programming Language :: Python :: 3.11
Classifier: Topic :: Software Development :: Libraries
Requires-Dist: langchain (>=0.1.0,<0.2.0)
Requires-Dist: langchain-core (>=0.1.10,<0.2.0)
Requires-Dist: pydantic (>=2.5.0,<3.0.0)
Requires-Dist: python-dotenv (>=1.1.0,<2.0.0)
Requires-Dist: requests (>=2.31.0,<3.0.0)
Project-URL: Bug Tracker, https://github.com/stackspot/langchain-stackspot-ai/issues
Project-URL: Documentation, https://langchain-stackspot-ai.readthedocs.io
Project-URL: Repository, https://github.com/stackspot/langchain-stackspot-ai
